py2ifttt/__init__.py
py2ifttt/py2ifttt.py
py2ifttt-1.0.0.dist-info/DESCRIPTION.rst
py2ifttt-1.0.0.dist-info/LICENSE.txt
py2ifttt-1.0.0.dist-info/METADATA
py2ifttt-1.0.0.dist-info/RECORD
py2ifttt-1.0.0.dist-info/WHEEL
py2ifttt-1.0.0.dist-info/metadata.json
py2ifttt-1.0.0.dist-info/top_level.txt
